auooo_nester.py
auooo_nester-1.4.0.dist-info/DESCRIPTION.rst
auooo_nester-1.4.0.dist-info/METADATA
auooo_nester-1.4.0.dist-info/RECORD
auooo_nester-1.4.0.dist-info/WHEEL
auooo_nester-1.4.0.dist-info/metadata.json
auooo_nester-1.4.0.dist-info/top_level.txt
