Metadata-Version: 2.0
Name: auooo-nester
Version: 1.4.0
Summary: A simple printer of nested lists, test for twine update
Home-page: http://www.auooo.com
Author: auooo
Author-email: mh245500@gmail.com
License: UNKNOWN
Platform: UNKNOWN
